stringformater03201/__init__.py
stringformater03201/stringformater.py
stringformatter03201-0.0.2.dist-info/METADATA
stringformatter03201-0.0.2.dist-info/WHEEL
stringformatter03201-0.0.2.dist-info/top_level.txt
stringformatter03201-0.0.2.dist-info/RECORD
