Metadata-Version: 2.1
Name: stringformatter03201
Version: 0.0.2
Summary: string formatter by eggSushi0320
Home-page: https://github.com/lazarus0320/oss.git
Author: eggSushi0320
Author-email: astar5327z@gmail.com
License: UNKNOWN
Keywords: stringformatter03201
Platform: UNKNOWN
Classifier: Programming Language :: Python :: 3.6
Classifier: Programming Language :: Python :: 3.7
Classifier: Programming Language :: Python :: 3.8
Classifier: Programming Language :: Python :: 3.9
Requires-Python: >=3.6
